{
  "_class": "shapePath",
  "booleanOperation": -1,
  "clippingMaskMode": 0,
  "do_objectID": "EE0AA1FC-A3AD-493E-B79D-3883E9B4E2C7",
  "edited": true,
  "exportOptions": {
    "_class": "exportOptions",
    "exportFormats": [
    ],
    "includedLayerIds": [
    ],
    "layerOptions": 0,
    "shouldTrim": false
  },
  "frame": {
    "_class": "rect",
    "constrainProportions": false,
    "height": 1.469387755103444,
    "width": 0.8741258741266231,
    "x": 1.76573426573298,
    "y": 2.0528211284505
  },
  "hasClippingMask": false,
  "isClosed": true,
  "isFixedToViewport": false,
  "isFlippedHorizontal": false,
  "isFlippedVertical": false,
  "isLocked": false,
  "isVisible": true,
  "layerListExpandedType": 0,
  "name": "Path",
  "nameIsFixed": false,
  "pointRadiusBehaviour": 1,
  "points": [
    {
      "_class": "curvePoint",
      "cornerRadius": 0,
      "curveFrom": "{0.34399999999732245, 0.88970588235285919}",
      "curveMode": 4,
      "curveTo": "{0.8720000000030268, 1}",
      "hasCurveFrom": true,
      "hasCurveTo": false,
      "point": "{0.8720000000030268, 1}"
    },
    {
      "_class": "curvePoint",
      "cornerRadius": 0,
      "curveFrom": "{0.1279999999969732, 0.2720588235311}",
      "curveMode": 2,
      "curveTo": "{0.1279999999969732, 0.75000000000055733}",
      "hasCurveFrom": true,
      "hasCurveTo": true,
      "point": "{0.1279999999969732, 0.50735294117684759}"
    },
    {
      "_class": "curvePoint",
      "cornerRadius": 0,
      "curveFrom": "{0.8720000000030268, 0}",
      "curveMode": 4,
      "curveTo": "{0.4040000000022701, 0.073529411766246625}",
      "hasCurveFrom": false,
      "hasCurveTo": true,
      "point": "{0.8720000000030268, 0}"
    }
  ],
  "resizingConstraint": 63,
  "resizingType": 0,
  "rotation": 0,
  "shouldBreakMaskChain": false,
  "style": {
    "_class": "style",
    "blur": {
      "_class": "blur",
      "center": "{0.5, 0.5}",
      "isEnabled": false,
      "motionAngle": 0,
      "radius": 9.003601440576965,
      "saturation": 1,
      "type": 0
    },
    "borderOptions": {
      "_class": "borderOptions",
      "dashPattern": [
      ],
      "isEnabled": true,
      "lineCapStyle": 0,
      "lineJoinStyle": 0
    },
    "borders": [
    ],
    "colorControls": {
      "_class": "colorControls",
      "brightness": 0,
      "contrast": 1,
      "hue": 0,
      "isEnabled": false,
      "saturation": 1
    },
    "contextSettings": {
      "_class": "graphicsContextSettings",
      "blendMode": 0,
      "opacity": 1
    },
    "do_objectID": "622B4C1A-1987-4545-9175-2DF2B6DC569B",
    "endMarkerType": 0,
    "fills": [
    ],
    "innerShadows": [
    ],
    "miterLimit": 10,
    "shadows": [
    ],
    "startMarkerType": 0,
    "windingRule": 1
  }
}