{
  "_class": "group",
  "booleanOperation": -1,
  "clippingMaskMode": 0,
  "do_objectID": "3CA80AB9-C84E-4998-9867-AF985102E3A5",
  "exportOptions": {
    "_class": "exportOptions",
    "exportFormats": [
    ],
    "includedLayerIds": [
    ],
    "layerOptions": 0,
    "shouldTrim": false
  },
  "frame": {
    "_class": "rect",
    "constrainProportions": false,
    "height": 42,
    "width": 329,
    "x": 23.05153901216909,
    "y": 7
  },
  "groupLayout": {
    "_class": "MSImmutableFreeformGroupLayout"
  },
  "hasClickThrough": false,
  "hasClippingMask": false,
  "isFixedToViewport": false,
  "isFlippedHorizontal": false,
  "isFlippedVertical": false,
  "isLocked": false,
  "isVisible": true,
  "layerListExpandedType": 0,
  "layers": [
    {
      "class": "symbolInstance",
      "id": "B4762077-2091-46D4-9B93-4CE8803A7C2D"
    },
    {
      "class": "symbolInstance",
      "id": "6CD43D6A-B88B-4591-A9A9-C9A3E397ECC3"
    },
    {
      "class": "symbolInstance",
      "id": "23F340EE-A775-45E0-8AC0-978157443492"
    },
    {
      "class": "symbolInstance",
      "id": "086566C4-0B26-43D7-9697-BE25FD33B0F6"
    },
    {
      "class": "symbolInstance",
      "id": "1F9C1A7A-2D19-4B2A-BBEC-2A7F1C828459"
    },
    {
      "class": "symbolInstance",
      "id": "8BA0CFB5-61D4-44C9-935C-AC772DE2808B"
    }
  ],
  "name": "bid ask spread",
  "nameIsFixed": true,
  "resizingConstraint": 41,
  "resizingType": 0,
  "rotation": 0,
  "shouldBreakMaskChain": false,
  "style": {
    "_class": "style",
    "blur": {
      "_class": "blur",
      "center": "{0.5, 0.5}",
      "isEnabled": false,
      "motionAngle": 0,
      "radius": 10,
      "saturation": 1,
      "type": 0
    },
    "borderOptions": {
      "_class": "borderOptions",
      "dashPattern": [
      ],
      "isEnabled": true,
      "lineCapStyle": 0,
      "lineJoinStyle": 0
    },
    "borders": [
    ],
    "colorControls": {
      "_class": "colorControls",
      "brightness": 0,
      "contrast": 1,
      "hue": 0,
      "isEnabled": false,
      "saturation": 1
    },
    "contextSettings": {
      "_class": "graphicsContextSettings",
      "blendMode": 0,
      "opacity": 1
    },
    "do_objectID": "A9A559A2-5EB2-4F76-987C-0B48F5D7E360",
    "endMarkerType": 0,
    "fills": [
    ],
    "innerShadows": [
    ],
    "miterLimit": 10,
    "shadows": [
    ],
    "startMarkerType": 0,
    "windingRule": 1
  }
}